randstrgen/__init__.py
randstrgen/generator.py
RandStrGen-0.2.0.dist-info/LICENSE
RandStrGen-0.2.0.dist-info/METADATA
RandStrGen-0.2.0.dist-info/WHEEL
RandStrGen-0.2.0.dist-info/top_level.txt
RandStrGen-0.2.0.dist-info/RECORD
