Metadata-Version: 2.1
Name: RandStrGen
Version: 0.2.0
Summary: A simple and flexible random string generator
Home-page: https://github.com/yourusername/RandStrGen
Author: lsw
Author-email: lsw@lwco.com
License: MIT
Classifier: Programming Language :: Python :: 3
Classifier: Intended Audience :: Developers
Classifier: License :: OSI Approved :: MIT License
Classifier: Operating System :: OS Independent
Requires-Python: >=3.6
License-File: LICENSE
